date_aware_logger-1.1.0.dist-info/licenses/LICENSE
dateawarelogger/__init__.py
dateawarelogger/logger.py
date_aware_logger-1.1.0.dist-info/METADATA
date_aware_logger-1.1.0.dist-info/WHEEL
date_aware_logger-1.1.0.dist-info/top_level.txt
date_aware_logger-1.1.0.dist-info/RECORD
