Metadata-Version: 2.4
Name: date-aware-logger
Version: 1.1.0
Summary: A customized rotational logger with monthly archiving and compression
Author-email: Achraf Bentaher <achraf.bentaher.ing@gmail.com>
License: MIT
Project-URL: Homepage, https://github.com/Skypouk/Rotational-Monthly-Logger
Project-URL: Repository, https://github.com/Skypouk/Rotational-Monthly-Logger.git
Project-URL: Issues, https://github.com/Skypouk/Rotational-Monthly-Logger.git/issues
Keywords: logging,logger,rotation,archiving,compression
Classifier: Development Status :: 4 - Beta
Classifier: Intended Audience :: Developers
Classifier: License :: OSI Approved :: MIT License
Classifier: Operating System :: OS Independent
Classifier: Programming Language :: Python :: 3
Classifier: Programming Language :: Python :: 3.7
Classifier: Programming Language :: Python :: 3.8
Classifier: Programming Language :: Python :: 3.9
Classifier: Programming Language :: Python :: 3.10
Classifier: Programming Language :: Python :: 3.11
Classifier: Programming Language :: Python :: 3.12
Classifier: Topic :: Software Development :: Libraries :: Python Modules
Classifier: Topic :: System :: Logging
Requires-Python: >=3.7
License-File: LICENSE
Provides-Extra: dev
Requires-Dist: pytest>=7.0; extra == "dev"
Requires-Dist: pytest-cov>=4.0; extra == "dev"
Requires-Dist: black>=22.0; extra == "dev"
Requires-Dist: flake8>=5.0; extra == "dev"
Requires-Dist: mypy>=1.0; extra == "dev"
Requires-Dist: pre-commit>=2.20; extra == "dev"
Dynamic: license-file
